LICENSE
MANIFEST.in
README.rst
pelicangit.py
setup.py
pelicangit/__init__.py
pelicangit/args.py
pelicangit/gitbindings.py
pelicangit/githook.py
pelicangit/log.py
pelicangit.egg-info/PKG-INFO
pelicangit.egg-info/SOURCES.txt
pelicangit.egg-info/dependency_links.txt
pelicangit.egg-info/entry_points.txt
pelicangit.egg-info/requires.txt
pelicangit.egg-info/top_level.txt